mcp_searxng_python/__init__.py
mcp_searxng_python/__main__.py
mcp_searxng_python/searxng_client.py
mcp_searxng_python/server.py
mcp_searxng_python/url_reader.py
mcp_searxng_python-0.1.2.dist-info/licenses/LICENSE
mcp_searxng_python-0.1.2.dist-info/METADATA
mcp_searxng_python-0.1.2.dist-info/WHEEL
mcp_searxng_python-0.1.2.dist-info/entry_points.txt
mcp_searxng_python-0.1.2.dist-info/top_level.txt
mcp_searxng_python-0.1.2.dist-info/RECORD
