Metadata-Version: 2.4
Name: mcp-searxng-python
Version: 0.1.2
Summary: SearXNG MCP Server implemented in Python with proxy support
Author-email: ferock <ferock@example.com>
Requires-Python: >=3.11
License-File: LICENSE
Requires-Dist: fastmcp>=2.10.6
Requires-Dist: httpx>=0.25.0
Requires-Dist: beautifulsoup4>=4.12.0
Requires-Dist: lxml>=4.9.0
Requires-Dist: markdownify>=0.11.6
Requires-Dist: typer>=0.16.0
Provides-Extra: dev
Requires-Dist: build; extra == "dev"
Requires-Dist: twine; extra == "dev"
Dynamic: license-file
